lib/pyramid_hawkauth/__init__.py
lib/pyramid_hawkauth/tests/__init__.py
lib/pyramid_hawkauth/tests/helper.py
lib/pyramid_hawkauth/tests/test_hawk_auth_policy.py
pyramid_hawkauth/__init__.py
pyramid_hawkauth/tests/__init__.py
pyramid_hawkauth/tests/helper.py
pyramid_hawkauth/tests/test_hawk_auth_policy.py
pyramid_hawkauth-2.0.0.dist-info/DESCRIPTION.rst
pyramid_hawkauth-2.0.0.dist-info/METADATA
pyramid_hawkauth-2.0.0.dist-info/RECORD
pyramid_hawkauth-2.0.0.dist-info/WHEEL
pyramid_hawkauth-2.0.0.dist-info/metadata.json
pyramid_hawkauth-2.0.0.dist-info/top_level.txt
