Metadata-Version: 2.0
Name: pyramid-hawkauth
Version: 2.0.0
Summary: A Pyramid authentication plugin for HAWK
Home-page: https://github.com/mozilla-services/pyramid_hawkauth
Author: Mozilla Services
Author-email: services-dev@mozilla.org
License: MPLv2.0
Keywords: authentication token hawk request signing
Platform: UNKNOWN
Classifier: Programming Language :: Python
Classifier: License :: OSI Approved :: Mozilla Public License 2.0 (MPL 2.0)
Classifier: Development Status :: 5 - Production/Stable
Requires-Dist: pyramid
Requires-Dist: hawkauthlib (>=2.0.0)
Requires-Dist: tokenlib (>=2.0.0)
Provides-Extra: test
Requires-Dist: webtest; extra == 'test'
